cli_nlp/__init__.py
cli_nlp/cache_manager.py
cli_nlp/cli.py
cli_nlp/command_runner.py
cli_nlp/completer.py
cli_nlp/config_manager.py
cli_nlp/context_manager.py
cli_nlp/history_manager.py
cli_nlp/models.py
cli_nlp/provider_manager.py
cli_nlp/template_manager.py
cli_nlp/utils.py
query_to_command-0.4.0.dist-info/METADATA
query_to_command-0.4.0.dist-info/WHEEL
query_to_command-0.4.0.dist-info/entry_points.txt
query_to_command-0.4.0.dist-info/licenses/LICENSE
query_to_command-0.4.0.dist-info/RECORD
