Metadata-Version: 2.4
Name: query-to-command
Version: 0.4.0
Summary: Natural Language to Shell Command Converter using OpenAI
License: MIT
License-File: LICENSE
Keywords: cli,nlp,openai,shell,command,natural-language
Author: Lawrence
Author-email: lawrence.carbon@gmail.com
Requires-Python: >=3.12,<4.0
Classifier: Development Status :: 4 - Beta
Classifier: Intended Audience :: Developers
Classifier: License :: OSI Approved :: MIT License
Classifier: Programming Language :: Python :: 3
Classifier: Programming Language :: Python :: 3.12
Classifier: Programming Language :: Python :: 3.13
Classifier: Programming Language :: Python :: 3.14
Classifier: Topic :: System :: Shells
Classifier: Topic :: Utilities
Requires-Dist: click (>=8.1.0,<9.0.0)
Requires-Dist: litellm (>=1.0.0,<2.0.0)
Requires-Dist: openai (>=1.0.0,<2.0.0)
Requires-Dist: prompt_toolkit (>=3.0.0,<4.0.0)
Requires-Dist: pydantic (>=2.0.0,<3.0.0)
Requires-Dist: rich (>=13.0.0,<14.0.0)
Project-URL: Homepage, https://github.com/lawrence-carbon/cli-nlp
Project-URL: Repository, https://github.com/lawrence-carbon/cli-nlp
